{
  "description": "Synthetic random DAG: 25 variables, 38 edges",
  "variables": {
    "X0": {
      "name": "X0"
    },
    "X1": {
      "name": "X1"
    },
    "X2": {
      "name": "X2"
    },
    "X3": {
      "name": "X3"
    },
    "X4": {
      "name": "X4"
    },
    "X5": {
      "name": "X5"
    },
    "X6": {
      "name": "X6"
    },
    "X7": {
      "name": "X7"
    },
    "X8": {
      "name": "X8"
    },
    "X9": {
      "name": "X9"
    },
    "X10": {
      "name": "X10"
    },
    "X11": {
      "name": "X11"
    },
    "X12": {
      "name": "X12"
    },
    "X13": {
      "name": "X13"
    },
    "X14": {
      "name": "X14"
    },
    "X15": {
      "name": "X15"
    },
    "X16": {
      "name": "X16"
    },
    "X17": {
      "name": "X17"
    },
    "X18": {
      "name": "X18"
    },
    "X19": {
      "name": "X19"
    },
    "X20": {
      "name": "X20"
    },
    "X21": {
      "name": "X21"
    },
    "X22": {
      "name": "X22"
    },
    "X23": {
      "name": "X23"
    },
    "X24": {
      "name": "X24"
    }
  },
  "topological_order": [
    "X0",
    "X1",
    "X2",
    "X3",
    "X4",
    "X5",
    "X6",
    "X7",
    "X8",
    "X9",
    "X10",
    "X11",
    "X12",
    "X13",
    "X14",
    "X15",
    "X16",
    "X17",
    "X18",
    "X19",
    "X20",
    "X21",
    "X22",
    "X23",
    "X24"
  ],
  "edges": [
    {
      "source": "X15",
      "target": "X22",
      "weight": 0.519,
      "sign": "excitatory"
    },
    {
      "source": "X20",
      "target": "X24",
      "weight": 0.649,
      "sign": "excitatory"
    },
    {
      "source": "X2",
      "target": "X17",
      "weight": -0.312,
      "sign": "inhibitory"
    },
    {
      "source": "X14",
      "target": "X23",
      "weight": 0.693,
      "sign": "excitatory"
    },
    {
      "source": "X8",
      "target": "X11",
      "weight": -0.575,
      "sign": "inhibitory"
    },
    {
      "source": "X1",
      "target": "X4",
      "weight": 0.763,
      "sign": "excitatory"
    },
    {
      "source": "X5",
      "target": "X23",
      "weight": 0.711,
      "sign": "excitatory"
    },
    {
      "source": "X18",
      "target": "X24",
      "weight": 0.414,
      "sign": "excitatory"
    },
    {
      "source": "X0",
      "target": "X20",
      "weight": 0.332,
      "sign": "excitatory"
    },
    {
      "source": "X14",
      "target": "X24",
      "weight": 0.616,
      "sign": "excitatory"
    },
    {
      "source": "X9",
      "target": "X21",
      "weight": 0.477,
      "sign": "excitatory"
    },
    {
      "source": "X20",
      "target": "X21",
      "weight": 0.747,
      "sign": "excitatory"
    },
    {
      "source": "X11",
      "target": "X17",
      "weight": 0.397,
      "sign": "excitatory"
    },
    {
      "source": "X1",
      "target": "X24",
      "weight": 0.322,
      "sign": "excitatory"
    },
    {
      "source": "X21",
      "target": "X24",
      "weight": -0.458,
      "sign": "inhibitory"
    },
    {
      "source": "X9",
      "target": "X23",
      "weight": 0.784,
      "sign": "excitatory"
    },
    {
      "source": "X3",
      "target": "X12",
      "weight": 0.485,
      "sign": "excitatory"
    },
    {
      "source": "X2",
      "target": "X7",
      "weight": 0.395,
      "sign": "excitatory"
    },
    {
      "source": "X4",
      "target": "X13",
      "weight": -0.562,
      "sign": "inhibitory"
    },
    {
      "source": "X9",
      "target": "X14",
      "weight": -0.465,
      "sign": "inhibitory"
    },
    {
      "source": "X13",
      "target": "X15",
      "weight": 0.716,
      "sign": "excitatory"
    },
    {
      "source": "X22",
      "target": "X23",
      "weight": 0.456,
      "sign": "excitatory"
    },
    {
      "source": "X13",
      "target": "X14",
      "weight": 0.702,
      "sign": "excitatory"
    },
    {
      "source": "X17",
      "target": "X19",
      "weight": 0.444,
      "sign": "excitatory"
    },
    {
      "source": "X16",
      "target": "X24",
      "weight": 0.37,
      "sign": "excitatory"
    },
    {
      "source": "X18",
      "target": "X21",
      "weight": -0.796,
      "sign": "inhibitory"
    },
    {
      "source": "X0",
      "target": "X1",
      "weight": 0.632,
      "sign": "excitatory"
    },
    {
      "source": "X2",
      "target": "X20",
      "weight": 0.69,
      "sign": "excitatory"
    },
    {
      "source": "X10",
      "target": "X17",
      "weight": 0.584,
      "sign": "excitatory"
    },
    {
      "source": "X4",
      "target": "X7",
      "weight": -0.743,
      "sign": "inhibitory"
    },
    {
      "source": "X6",
      "target": "X24",
      "weight": 0.536,
      "sign": "excitatory"
    },
    {
      "source": "X5",
      "target": "X22",
      "weight": 0.682,
      "sign": "excitatory"
    },
    {
      "source": "X2",
      "target": "X6",
      "weight": 0.577,
      "sign": "excitatory"
    },
    {
      "source": "X15",
      "target": "X17",
      "weight": 0.452,
      "sign": "excitatory"
    },
    {
      "source": "X12",
      "target": "X21",
      "weight": -0.582,
      "sign": "inhibitory"
    },
    {
      "source": "X15",
      "target": "X20",
      "weight": -0.596,
      "sign": "inhibitory"
    },
    {
      "source": "X10",
      "target": "X14",
      "weight": 0.417,
      "sign": "excitatory"
    },
    {
      "source": "X1",
      "target": "X7",
      "weight": -0.659,
      "sign": "inhibitory"
    }
  ],
  "adjacency_matrix": {
    "order": [
      "X0",
      "X1",
      "X2",
      "X3",
      "X4",
      "X5",
      "X6",
      "X7",
      "X8",
      "X9",
      "X10",
      "X11",
      "X12",
      "X13",
      "X14",
      "X15",
      "X16",
      "X17",
      "X18",
      "X19",
      "X20",
      "X21",
      "X22",
      "X23",
      "X24"
    ],
    "matrix": [
      [
        0,
        1,
        0,
        0,
        0,
        0,
        0,
        0,
        0,
        0,
        0,
        0,
        0,
        0,
        0,
        0,
        0,
        0,
        0,
        0,
        1,
        0,
        0,
        0,
        0
      ],
      [
        0,
        0,
        0,
        0,
        1,
        0,
        0,
        1,
        0,
        0,
        0,
        0,
        0,
        0,
        0,
        0,
        0,
        0,
        0,
        0,
        0,
        0,
        0,
        0,
        1
      ],
      [
        0,
        0,
        0,
        0,
        0,
        0,
        1,
        1,
        0,
        0,
        0,
        0,
        0,
        0,
        0,
        0,
        0,
        1,
        0,
        0,
        1,
        0,
        0,
        0,
        0
      ],
      [
        0,
        0,
        0,
        0,
        0,
        0,
        0,
        0,
        0,
        0,
        0,
        0,
        1,
        0,
        0,
        0,
        0,
        0,
        0,
        0,
        0,
        0,
        0,
        0,
        0
      ],
      [
        0,
        0,
        0,
        0,
        0,
        0,
        0,
        1,
        0,
        0,
        0,
        0,
        0,
        1,
        0,
        0,
        0,
        0,
        0,
        0,
        0,
        0,
        0,
        0,
        0
      ],
      [
        0,
        0,
        0,
        0,
        0,
        0,
        0,
        0,
        0,
        0,
        0,
        0,
        0,
        0,
        0,
        0,
        0,
        0,
        0,
        0,
        0,
        0,
        1,
        1,
        0
      ],
      [
        0,
        0,
        0,
        0,
        0,
        0,
        0,
        0,
        0,
        0,
        0,
        0,
        0,
        0,
        0,
        0,
        0,
        0,
        0,
        0,
        0,
        0,
        0,
        0,
        1
      ],
      [
        0,
        0,
        0,
        0,
        0,
        0,
        0,
        0,
        0,
        0,
        0,
        0,
        0,
        0,
        0,
        0,
        0,
        0,
        0,
        0,
        0,
        0,
        0,
        0,
        0
      ],
      [
        0,
        0,
        0,
        0,
        0,
        0,
        0,
        0,
        0,
        0,
        0,
        1,
        0,
        0,
        0,
        0,
        0,
        0,
        0,
        0,
        0,
        0,
        0,
        0,
        0
      ],
      [
        0,
        0,
        0,
        0,
        0,
        0,
        0,
        0,
        0,
        0,
        0,
        0,
        0,
        0,
        1,
        0,
        0,
        0,
        0,
        0,
        0,
        1,
        0,
        1,
        0
      ],
      [
        0,
        0,
        0,
        0,
        0,
        0,
        0,
        0,
        0,
        0,
        0,
        0,
        0,
        0,
        1,
        0,
        0,
        1,
        0,
        0,
        0,
        0,
        0,
        0,
        0
      ],
      [
        0,
        0,
        0,
        0,
        0,
        0,
        0,
        0,
        0,
        0,
        0,
        0,
        0,
        0,
        0,
        0,
        0,
        1,
        0,
        0,
        0,
        0,
        0,
        0,
        0
      ],
      [
        0,
        0,
        0,
        0,
        0,
        0,
        0,
        0,
        0,
        0,
        0,
        0,
        0,
        0,
        0,
        0,
        0,
        0,
        0,
        0,
        0,
        1,
        0,
        0,
        0
      ],
      [
        0,
        0,
        0,
        0,
        0,
        0,
        0,
        0,
        0,
        0,
        0,
        0,
        0,
        0,
        1,
        1,
        0,
        0,
        0,
        0,
        0,
        0,
        0,
        0,
        0
      ],
      [
        0,
        0,
        0,
        0,
        0,
        0,
        0,
        0,
        0,
        0,
        0,
        0,
        0,
        0,
        0,
        0,
        0,
        0,
        0,
        0,
        0,
        0,
        0,
        1,
        1
      ],
      [
        0,
        0,
        0,
        0,
        0,
        0,
        0,
        0,
        0,
        0,
        0,
        0,
        0,
        0,
        0,
        0,
        0,
        1,
        0,
        0,
        1,
        0,
        1,
        0,
        0
      ],
      [
        0,
        0,
        0,
        0,
        0,
        0,
        0,
        0,
        0,
        0,
        0,
        0,
        0,
        0,
        0,
        0,
        0,
        0,
        0,
        0,
        0,
        0,
        0,
        0,
        1
      ],
      [
        0,
        0,
        0,
        0,
        0,
        0,
        0,
        0,
        0,
        0,
        0,
        0,
        0,
        0,
        0,
        0,
        0,
        0,
        0,
        1,
        0,
        0,
        0,
        0,
        0
      ],
      [
        0,
        0,
        0,
        0,
        0,
        0,
        0,
        0,
        0,
        0,
        0,
        0,
        0,
        0,
        0,
        0,
        0,
        0,
        0,
        0,
        0,
        1,
        0,
        0,
        1
      ],
      [
        0,
        0,
        0,
        0,
        0,
        0,
        0,
        0,
        0,
        0,
        0,
        0,
        0,
        0,
        0,
        0,
        0,
        0,
        0,
        0,
        0,
        0,
        0,
        0,
        0
      ],
      [
        0,
        0,
        0,
        0,
        0,
        0,
        0,
        0,
        0,
        0,
        0,
        0,
        0,
        0,
        0,
        0,
        0,
        0,
        0,
        0,
        0,
        1,
        0,
        0,
        1
      ],
      [
        0,
        0,
        0,
        0,
        0,
        0,
        0,
        0,
        0,
        0,
        0,
        0,
        0,
        0,
        0,
        0,
        0,
        0,
        0,
        0,
        0,
        0,
        0,
        0,
        1
      ],
      [
        0,
        0,
        0,
        0,
        0,
        0,
        0,
        0,
        0,
        0,
        0,
        0,
        0,
        0,
        0,
        0,
        0,
        0,
        0,
        0,
        0,
        0,
        0,
        1,
        0
      ],
      [
        0,
        0,
        0,
        0,
        0,
        0,
        0,
        0,
        0,
        0,
        0,
        0,
        0,
        0,
        0,
        0,
        0,
        0,
        0,
        0,
        0,
        0,
        0,
        0,
        0
      ],
      [
        0,
        0,
        0,
        0,
        0,
        0,
        0,
        0,
        0,
        0,
        0,
        0,
        0,
        0,
        0,
        0,
        0,
        0,
        0,
        0,
        0,
        0,
        0,
        0,
        0
      ]
    ]
  },
  "scm_parameters": {
    "noise_variance": 0.3,
    "weights": {
      "w_X15X22": 0.519,
      "w_X20X24": 0.649,
      "w_X2X17": -0.312,
      "w_X14X23": 0.693,
      "w_X8X11": -0.575,
      "w_X1X4": 0.763,
      "w_X5X23": 0.711,
      "w_X18X24": 0.414,
      "w_X0X20": 0.332,
      "w_X14X24": 0.616,
      "w_X9X21": 0.477,
      "w_X20X21": 0.747,
      "w_X11X17": 0.397,
      "w_X1X24": 0.322,
      "w_X21X24": -0.458,
      "w_X9X23": 0.784,
      "w_X3X12": 0.485,
      "w_X2X7": 0.395,
      "w_X4X13": -0.562,
      "w_X9X14": -0.465,
      "w_X13X15": 0.716,
      "w_X22X23": 0.456,
      "w_X13X14": 0.702,
      "w_X17X19": 0.444,
      "w_X16X24": 0.37,
      "w_X18X21": -0.796,
      "w_X0X1": 0.632,
      "w_X2X20": 0.69,
      "w_X10X17": 0.584,
      "w_X4X7": -0.743,
      "w_X6X24": 0.536,
      "w_X5X22": 0.682,
      "w_X2X6": 0.577,
      "w_X15X17": 0.452,
      "w_X12X21": -0.582,
      "w_X15X20": -0.596,
      "w_X10X14": 0.417,
      "w_X1X7": -0.659
    }
  }
}